{"id": "251545642", "presentation_url": "https://fr.slideshare.net/slideshow/les-franais-et-llection-prsidentielle-2022-251545642/251545642", "title": "Les Fran\u00e7ais et l'\u00e9lection pr\u00e9sidentielle 2022", "author": "contactElabe", "date": "2022-04-08", "len": 31, "description": "Les Fran\u00e7ais et l'\u00e9lection pr\u00e9sidentielle 2022", "lang": "fr", "dim": {"height": 405, "width": 720}, "like": 0, "view": 8448, "transcript": ["Les Fran\u00e7ais et l\u2019\u00e9lection pr\u00e9sidentielle 2022\nSondage ELABE pour BFMTV, L\u2019EXPRESS et SFR\n8 avril 2022\n ", "- 2 -\nEtude ELABE r\u00e9alis\u00e9e pour BFMTV, L\u2019EXPRESS et SFR.\nFiche technique\nInterrogation\nEchantillon de 1 801 personnes repr\u00e9sentatif des r\u00e9sidents de France m\u00e9tropolitaine \u00e2g\u00e9s de 18 ans et plus, dont 1 691\ninscrits sur les listes \u00e9lectorales\nConstitution de l\u2019\u00e9chantillon\nLa repr\u00e9sentativit\u00e9 de l\u2019\u00e9chantillon a \u00e9t\u00e9 assur\u00e9e selon la m\u00e9thode des quotas appliqu\u00e9e aux variables suivantes : sexe,\n\u00e2ge et profession de l\u2019interview\u00e9 apr\u00e8s stratification par r\u00e9gion et cat\u00e9gorie d\u2019agglom\u00e9ration.\nMode de recueil et dates de terrain\nInterrogation par Internet du 7 au 8 avril 2022.\nELABE rappelle que les r\u00e9sultats de ce sondage doivent \u00eatre interpr\u00e9t\u00e9s comme une indication de l\u2019\u00e9tat du rapport de force politique actuel en France m\u00e9tropolitaine dans la perspective de l\u2019\u00e9lection\npr\u00e9sidentielle de 2022. Ils ne constituent en aucun cas un \u00e9l\u00e9ment pr\u00e9dictif des r\u00e9sultats le jour du vote.\nLa notice de ce sondage peut \u00eatre consult\u00e9e sur le site internet de la Commission des sondages : www.commission-des-sondages.fr\nToute publication ou toute reprise de ce sondage doit faire figurer la m\u00e9thodologie et les marges d\u2019erreurs :\n\u00ab Echantillon de 1 801 personnes repr\u00e9sentatif des r\u00e9sidents de France m\u00e9tropolitaine \u00e2g\u00e9s de 18 ans et plus, dont 1 691 inscrits sur les listes \u00e9lectorales. Interrogation par Internet du 7 au 8 avril 2022..\nLa repr\u00e9sentativit\u00e9 de l\u2019\u00e9chantillon a \u00e9t\u00e9 assur\u00e9e selon la m\u00e9thode des quotas appliqu\u00e9e aux variables suivantes: sexe, \u00e2ge, cat\u00e9gorie socio-professionnelle, r\u00e9gion de r\u00e9sidence et cat\u00e9gorie d\u2019agglom\u00e9ration.\nPour les questions d\u2019intention de vote, seules les personnes inscrites sur les listes \u00e9lectorales et ayant l\u2019intention d\u2019aller voter sont prises en compte.\nPour les questions d\u2019opinion, l\u2019ensemble de l\u2019\u00e9chantillon est pris en compte\nMarge d\u2019erreur comprise entre 1 et 2,8 points de pourcentage. \u00bb\nLes Fran\u00e7ais et l'\u00e9lection pr\u00e9sidentielle 2022\n8 avril 2022\n ", "- 3 -\nMarges d\u2019erreur\nPour\nun pourcentage de :\nLa marge d\u2019erreur\nest de :\nLe r\u00e9sultat r\u00e9el se situe\ndans une fourchette\nentre :\n5 +/- 1 4 et 6\n10 +/- 1,4 8,6 et 11,4\n15 +/- 1,7 13,3 et 16,7\n20 +/- 1,8 18,2 et 21,8\n25 +/- 2 23 et 27\n30 +/- 2,1 27,9 et 32,1\n35 +/- 2,2 32,8 et 37,2\n40 +/- 2,3 37,7 et 42,3\n45 +/- 2,3 42,7 et 47,3\n50 +/- 2,3 47,7 et 52,3\n55 +/- 2,3 52,7 et 57,3\n60 +/- 2,3 57,7 et 62,3\n65 +/- 2,2 62,8 et 67,2\n70 +/- 2,1 67,9 et 72,1\n75 +/- 2 73 et 77\n80 +/- 1,8 78,2 et 81,8\n85 +/- 1,7 83,3 et 86,7\n90 +/- 1,4 88,6 et 91,4\n95 +/- 1 94 et 96\nQuestions d\u2019opinion\nMarges d\u2019erreur (niveau de confiance 95%) pour un \u00e9chantillon\nde 1 800 personnes :\nExemple de lecture : Pour un r\u00e9sultat observ\u00e9 de 25%, il y a 95% de chances\npour que le r\u00e9sultat r\u00e9el soit compris entre 23% et 27%.\nExemple de lecture : Pour un r\u00e9sultat observ\u00e9 de 25%, il y a 95% de chances\npour que le r\u00e9sultat r\u00e9el soit compris entre 22,5% et 27,5%.\nPour\nun pourcentage de :\nLa marge d\u2019erreur\nest de :\nLe r\u00e9sultat r\u00e9el se situe\ndans une fourchette\nentre :\n5 +/- 1,2 3,8 et 6,2\n10 +/- 1,7 8,3 et 11,7\n15 +/- 2 13 et 17\n20 +/- 2,3 17,7 et 22,3\n25 +/- 2,5 22,5 et 27,5\n30 +/- 2,6 27,4 et 32,6\n35 +/- 2,7 32,3 et 37,7\n40 +/- 2,8 37,2 et 42,8\n45 +/- 2,8 42,2 et 47,8\n50 +/- 2,8 47,2 et 52,8\n55 +/- 2,8 52,2 et 57,8\n60 +/- 2,8 57,2 et 62,8\n65 +/- 2,7 62,3 et 67,7\n70 +/- 2,6 67,4 et 72,6\n75 +/- 2,5 72,5 et 77,5\n80 +/- 2,3 77,7 et 82,3\n85 +/- 2 83 et 87\n90 +/- 1,7 88,3 et 91,7\n95 +/- 1,2 93,8 et 96,2\nQuestions d\u2019intentions de vote\nMarges d\u2019erreur (niveau de confiance 95%) pour un \u00e9chantillon\nde 1 200 personnes :\nLes Fran\u00e7ais et l'\u00e9lection pr\u00e9sidentielle 2022\n8 avril 2022\n ", "R\u00e9sultats nationaux aux derni\u00e8res \u00e9lections (en exprim\u00e9s)\nElection pr\u00e9sidentielle 1er tour\n23 avril 2017\n24,0\n21,3\n20,0\n19,6\n6,4\n4,7\n3,9\nEmmanuel Macron\nMarine LE PEN\nFran\u00e7ois FILLON\nJean-Luc MELENCHON\nBeno\u00eet HAMON\nNicolas DUPONT-AIGNAN\nAutres candidats\nParticipation 77,8%\n23,3\n22,4\n13,5\n8,5\n6,3\n6,2\n3,5\n3,3\n2,5\n2,5\n2,2\n1,8\n4,0\nRN\nLREM\nEELV\nLR\nLFI\nPS\nDLF\nG\u00e9n\u00e9ration.s\nUDI\nPCF\nParti Animaliste\nUrgence Ecologie\nAutres listes\nElections europ\u00e9ennes\n26 mai 2019\nParticipation 50,1%\nElection pr\u00e9sidentielle 2nd tour\n7 mai 2017\n33,9\n66,1\nMarine Le Pen\nEmmanuel Macron\nParticipation 74,6%\n- 4 -\nLes Fran\u00e7ais et l'\u00e9lection pr\u00e9sidentielle 2022\n8 avril 2022\n ", "Principaux enseignements\nL\u2019intention d\u2019aller voter progresse en 3 jours : 65% (+3) des inscrits se disent tout \u00e0 fait certains de se\nrendre aux urnes et 13% (=) l\u2019envisagent s\u00e9rieusement\nA partir d\u2019une \u00e9chelle allant de 0 \u00e0 10 (o\u00f9 0 signifie \u00eatre tout \u00e0 fait certain de ne pas aller voter et 10 \u00eatre tout \u00e0 faitcertain d\u2019aller voter, les\nnotes interm\u00e9diaires permettant aux sond\u00e9s de nuancer leur intention),65% (+3 par rapport au 5 avril) des inscrits se disent tout \u00e0 fait\ncertain d\u2019aller voter (note 10) et 13% (=) l\u2019envisagent s\u00e9rieusement (note 9).\nEn terme d\u2019\u00e2ge, les inscrits \u00e2g\u00e9s de 50 ans et plus (84% notes 9-10) et les cadres et professions interm\u00e9diaires (79%) ont davantage l\u2019intention\nd\u2019aller voter que les moins de 50 ans (72%) et les cat\u00e9gories populaires (73%).\nLa certitude d\u2019aller voter (65% note 10) est nettement inf\u00e9rieure \u00e0 celle mesur\u00e9e en 2017 \u00e0 la m\u00eame p\u00e9riode, c\u2019est-\u00e0-dire 2 jours avant le 1er\ntour (71%, soit 6 points de moins).\nELABE projette un niveau de participation au 1er tour de l\u2019\u00e9lection pr\u00e9sidentielle 2022 entre 70% et 74%.\n- 5 -\nLes Fran\u00e7ais et l'\u00e9lection pr\u00e9sidentielle 2022\n8 avril 2022\n ", "Principaux enseignements\nAu 1er tour, l\u2019\u00e9cart n\u2019a jamais \u00e9t\u00e9 aussi serr\u00e9 entre Emmanuel Macron en baisse (26%, -2) et Marine Le Pen (25%, +2) qui\npoursuit sa dynamique positive. Jean-Luc M\u00e9lenchon progresse et atteint 17.5% (+2).\nE. Zemmour (8.5%, -0.5) et V. P\u00e9cresse (8%, =) seraient distanc\u00e9s\nEmmanuel Macron est cr\u00e9dit\u00e9 de 26% (-2) des intentions de votes exprim\u00e9es. Si le Pr\u00e9sident sortant conserverait un soutien tr\u00e8s solide de ses propres \u00e9lecteurs de 2017\n(76% voteraient \u00e0 nouveau pour lui) et d\u2019un soutien important des \u00e9lecteurs de Fran\u00e7ois Fillon (24%) et de Beno\u00eet Hamon (21%), il est en baisse dans la plupart des\n\u00e9lectorats et revient \u00e0 un niveau ant\u00e9rieur \u00e0 la guerre en Ukraine (\u00ab l\u2019effet drapeau \u00bb qui s\u2019estompe).\nMarine Le Pen poursuit sa dynamique positive (25%, +2 en 3 jours, +10 en 1 mois) et n\u2019est plus qu\u2019\u00e0 1 point d\u2019Emmanuel Macron.\nMarine Le Pen progresse et n\u2019a jamais eu un soutien aussi \u00e9lev\u00e9 de ses \u00e9lecteurs de 2017 (76%, +5 en 3 jours, +26 en 1 mois), ceux de Fran\u00e7ois Fillon (17%, +6 en 3 jours,\n+15 en 1 mois) et des \u00e9lecteurs qui se positionnent politiquement \u00e0 droite (33%, +9 en 3 jours, +17 en 1 mois). Marine Le Penprogresse aupr\u00e8s des populations les plus\nenclines \u00e0 voter pour elle, notamment les Fran\u00e7ais qui doivent se restreindre pour boucler leurs fins de mois (36%, +6), et resterait en t\u00eate au sein des cat\u00e9gories\npopulaires (37%).\nJean-Luc M\u00e9lenchon progresse et atteint 17.5% (+2) des intentions de vote exprim\u00e9es. Le candidat Insoumis aurait les voix de 59% de ses \u00e9lecteurs de 2017 et atteint un\nniveau de soutien au plus haut chez les \u00e9lecteurs de Beno\u00eet Hamon (32%, +12) et chez les abstentionnistes (29%, +10). Jean-Luc M\u00e9lenchon ferait un bon score chez les\nmoins de 35 ans (27%).\nEric Zemmour (8.5%, -0.5) et Val\u00e9rie P\u00e9cresse (8%, =) seraient distanc\u00e9s\nLe candidat Reconqu\u00eate disposerait des voix de 16% (-1) des \u00e9lecteurs de Fran\u00e7ois Fillon et de 13% (-3) des \u00e9lecteurs de 2017 de Marine Le Pen.\nVal\u00e9rie P\u00e9cresse n\u2019aurait qu\u2019un soutien tr\u00e8s partiel des \u00e9lecteurs de Fran\u00e7ois Fillon (32% d\u2019entre eux voteraient pour elle, 24% pour E. Macron, 17% Marine Le Pen et 16%\nE. Zemmour) et aucune r\u00e9serve de voix en dehors.\nYannick Jadot est en baisse (4%, -1), Fabien Roussel (2.5%, =) et Anne Hidalgo (2%, =) sont stables.\nJean Lassalle est cr\u00e9dit\u00e9 de 2.5% (-0.5) des intentions de vote exprim\u00e9es, Nicolas Dupont-Aignan 2.5% (+0.5), les autres candidats moins de 2%.\n- 6 -\nLes Fran\u00e7ais et l'\u00e9lection pr\u00e9sidentielle 2022\n8 avril 2022\n ", "Principaux enseignements\n76% (+4 en 3 jours) des \u00e9lecteurs se disent s\u00fbrs de leur choix, 24% (-4) pourraient changer d\u2019avis d\u2019ici\ndimanche\nA ce jour, 76% (+4 en 3 jours) des \u00e9lecteurs qui ont l\u2019intention d\u2019aller voter (notes 9 \u00e0 10) se disent certains de leur choix. A l\u2019inverse,\n24% (-4) d\u2019entre eux pourraient changer d\u2019avis d\u2019ici \u00e0 l\u2019\u00e9lection (soit 8 millions de personnes).\nA 2 jours du 1er tour de l\u2019\u00e9lection pr\u00e9sidentielle, les \u00e9lecteurs qui sont les plus s\u00fbrs de leur choix sont ceux de Marine Le Pen (85%, +1 en\n3 jours) et d\u2019Emmanuel Macron (84%, +2), devan\u00e7ant les potentiels \u00e9lecteurs d'\u00c9ric Zemmour (81%, +2), de Jean-Luc M\u00e9lenchon (80%,\n+4) et de Val\u00e9rie P\u00e9cresse (78%, +4).\nA quelques jours du scrutin, la suret\u00e9 du choix des potentiels \u00e9lecteurs de Yannick Jadot reste tr\u00e8s fragile (47% s\u00fbrs, 53% pourraient\nchanger d\u2019avis).\n- 7 -\nLes Fran\u00e7ais et l'\u00e9lection pr\u00e9sidentielle 2022\n8 avril 2022\n ", "Principaux enseignements\nAu 2nd tour, Emmanuel Macron (51%, -2) ne dispose plus que d\u2019une l\u00e9g\u00e8re avance sur Marine Le Pen\n(49%, +2) dans les intentions de vote\nCompte-tenu des r\u00e9sultats mesur\u00e9s au 1er tour et des marges d\u2019erreur (cf. slide 19), la configurations E. Macron / M. Le Pen est aujourd\u2019hui la seule hypoth\u00e8se\nplausible.\nLe resserrement de l\u2019\u00e9cart entre ces deux candidats s\u2019explique par deux ph\u00e9nom\u00e8nes :\n\u2022 Une dynamique 1er tour tr\u00e8s favorable \u00e0 Marine Le Pen (+2) et d\u00e9favorable \u00e0 Emmanuel Macron (-2)\n\u2022 Un meilleur report de voix des \u00e9lecteurs de 1er tour d'\u00c9ric Zemmour (82%, +10) et de Val\u00e9rie P\u00e9cresse (34%, +6) en faveur de Marine\nLe Pen, par rapport au d\u00e9but de semaine\nEmmanuel Macron conserve une l\u00e9g\u00e8re avance gr\u00e2ce \u00e0 de bons reports de voix des \u00e9lecteurs de 1er tour de Yannick Jadot (61%, contre\n27% qui s\u2019abstiendraient) et dans une moindre mesure de Val\u00e9rie P\u00e9cresse (42%).\nDans cette configuration, les \u00e9lecteurs de 1er tour de Jean-Luc M\u00e9lenchon seraient divis\u00e9s : 4 sur 10 s\u2019abstiendraient, 1 tiers voterait\npour Emmanuel Macron et 1 quart pour Marine Le Pen\n- 8 -\nLes Fran\u00e7ais et l'\u00e9lection pr\u00e9sidentielle 2022\n8 avril 2022\n ", "Principaux enseignements\nPlus d\u20191 Fran\u00e7ais sur 2 pronostique une r\u00e9\u00e9lection d\u2019Emmanuel Macron (54%, -6) malgr\u00e9 une baisse\n22% (+2) anticipent une victoire de Marine Le Pen et 10% (+2) de Jean-Luc M\u00e9lenchon\nA ce jour, 54% (-6 par rapport au 5 avril 2022) des Fran\u00e7ais font le pronostic d\u2019une r\u00e9\u00e9lection d\u2019Emmanuel Macron en avril prochain.\n22% (+2) anticipent une victoire de Marine Le Pen et 10% (+2) de Jean-Luc M\u00e9lenchon.\n3% (-1) font le pronostic d\u2019une victoire d'\u00c9ric Zemmour et 2% (=) Val\u00e9rie P\u00e9cresse.\nLes autres candidats sont cit\u00e9s par moins de 3% des Fran\u00e7ais.\nLes \u00e9lecteurs qui ont l\u2019intention de voter pour Marine Le Pen croient de plus en plus \u00e0 une victoire de leurcandidate (73%, +9 en 3 jours) et de\nmoins en moins \u00e0 une victoire d\u2019Emmanuel Macron (24%,-9).\nLes \u00e9lecteurs potentiels d\u2019Emmanuel Macron s\u2019attendent en masse \u00e0 une r\u00e9\u00e9lection de leur champion.\nLes \u00e9lecteurs potentiels de Jean-Luc M\u00e9lenchon retrouvent un certain optimisme quant \u00e0 une victoire de leur candidat (52%, +4 en3 jours) et\ns\u2019attendent un peu moins \u00e0 une victoire d\u2019Emmanuel Macron (36%,-4).\n6 \u00e9lecteurs potentiels de Val\u00e9rie P\u00e9cresse sur 10 pensent qu\u2019Emmanuel Macron sera r\u00e9\u00e9lu (62%), seule une minorit\u00e9 d\u2019entre euxanticipe une\nvictoire de leur candidate (28%).\nEnfin, les \u00e9lecteurs potentiels d'\u00c9ric Zemmour sont de moins en moins nombreux \u00e0 pronostiquer une victoire de leur candidat (31%, -15) au\nprofit d\u2019une r\u00e9\u00e9lection d\u2019Emmanuel Macron (38%, +7) ou d\u2019une victoire de Marine Le Pen (30%, +11).\n- 9 -\nLes Fran\u00e7ais et l'\u00e9lection pr\u00e9sidentielle 2022\n8 avril 2022\n ", "65\n65\n60\n58\n61\n69\n71\n64\n67\n63\n54\n71\n63\n63\n69\n69\n78\n74\n49\n78\n78\n70\n71\n73\n83\n85\n78\n79\n75\n71\n85\n71\n76\n82\n86\n89\n85\n61\nSEXE\nHomme\nFemme\nAGE\n18-24 ans\n25-34 ans\n35-49 ans\n50-64 ans\n65 ans et plus\nPROFESSION\nCadre et prof. sup.\nProfession interm\u00e9diaire\nEmploy\u00e9\nOuvrier\nRetrait\u00e9\nAutres inactifs\nVOTE PRESIDENTIELLE 2017\u2026\nJean-Luc MELENCHON\nBeno\u00eet HAMON\nEmmanuel MACRON\nFran\u00e7ois FILLON\nMarine LE PEN\nAbstention, vote blanc ou nul\nL\u2019intention d\u2019aller voter progresse en 3 jours : 65% (+3) des inscrits se disent tout \u00e0\nfait certains de se rendre aux urnes et 13% (=) l\u2019envisagent s\u00e9rieusement\n- 10 -\n4 1 1 1 1 2 2 4 6\n13\n65\n0 1 2 3 4 5 6 7 8 9 10\nTout \u00e0 fait certain\nde ne pas aller voter\nTout \u00e0 fait certain\nd\u2019aller voter\n65%\nSe disent tout \u00e0 fait\ncertain d\u2019aller voter\n(note 10)\n13%\nEnvisagent\ns\u00e9rieusement d\u2019aller\nvoter (note 9)\n22%\nN\u2019iront probablement\nvoire certainement pas\nvoter (notes 0-8)\nQuestion : La prochaine \u00e9lection pr\u00e9sidentielle a lieu ce dimanche 10 avril 2022. Sur une \u00e9chelle allant de \u00ab 0 \u00bb \u00e0 \u00ab 10 \u00bb, quelle est la probabilit\u00e9 que vous alliez voter\n\u00e0 l\u2019\u00e9lection pr\u00e9sidentielle qui aura lieu ce dimanche 10 avril 2022 ? Sachant que : 0 signifie que vous \u00eates tout \u00e0 fait certain de ne pas aller voter et 10 que vous \u00eates tout\n\u00e0 fait certain d\u2019aller voter. Les notes interm\u00e9diaires vous permettent de nuancer votre intention. - Inscrits sur les listes \u00e9lectorales - En %\n(+3)\n(=)\n(-3)*\nSEXE\nAGE\nPROFESSION\n37 Notes 9 \u00e0 10\nTout \u00e0 fait certain d\u2019aller voter (note 10)\nVOTE PRESIDENTIELLE 2017 (T1)\n(*) Evolutions par rapport \u00e0 l\u2019enqu\u00eate ELABE/BFMTV/L\u2019EXPRESS/SFR r\u00e9alis\u00e9e du 4 au 5 avril 2022\nLes Fran\u00e7ais et l'\u00e9lection pr\u00e9sidentielle 2022\n8 avril 2022\n(-5)\n(+6)\n(+5)\n(+9)\n(+9)\n(+9)\n(+8)\n(+5)\n(-5)\n(+5)\n(+5)\n(+9)\n ", "- 11 -\nLa certitude d\u2019aller voter (65% note 10) est nettement inf\u00e9rieure \u00e0 celle mesur\u00e9e en 2017 \u00e0 la\nm\u00eame p\u00e9riode, c\u2019est-\u00e0-dire 2 jours avant le 1er tour (71%, soit 6 points de moins).\n54\n56 55\n53 54 55\n57 56\n59 58\n61\n63\n62\n65\n61\n57\n59 59\n62 62\n64 64 63\n68\n71\n30\n28 29 29 29 28\n26 27\n25 26 25\n22\n25\n22\n25\n28 24\n24\n23 22\n22 23\n18 17\n16 16 16\n18 17 17 17 17\n16\n16 14 15\n13 13\n14 15\n17\n14 15 14 14 14 14\n12\nJ-100\nJ-97\nJ-94\nJ-91\nJ-88\nJ-85\nJ-82\nJ-79\nJ-76\nJ-73\nJ-70\nJ-67\nJ-64\nJ-61\nJ-58\nJ-55\nJ-52\nJ-49\nJ-46\nJ-43\nJ-40\nJ-37\nJ-34\nJ-31\nJ-28\nJ-25\nJ-22\nJ-19\nJ-16\nJ-13\nJ-10\nJ-7\nJ-4\nJ-1\n2022\nTout \u00e0 fait certain d\u2019aller\nvoter (note 10)\n2017\n2022\nAbstentionnistes probables\nvoire certains (note 0-8)\n2017\n2022\nEnvisagent s\u00e9rieusement\nd\u2019aller voter (note 9)\n2017\nLes Fran\u00e7ais et l'\u00e9lection pr\u00e9sidentielle 2022\n8 avril 2022\n ", "Projection ELABE du niveau de participation au 1er tour de l\u2019\u00e9lection pr\u00e9sidentielle 2022\n- 12 -\nLes Fran\u00e7ais et l'\u00e9lection pr\u00e9sidentielle 2022\n8 avril 2022\nProjection ELABE du niveau de participation\nau 1er tour de l\u2019\u00e9lection pr\u00e9sidentielle 2022 :\nentre 70% et 74%\n71,6\n83,8 79,5 77,5\n2002 2007 2012 2017\nRappel du taux de participation depuis 2002\n(en % des inscrits)\n ", "- 13 -\n1\n0,5\n2,5\n17,5\n2\n4\n26\n8\n2,5\n25\n8,5\n2,5\nQuestion : Le premier tour de l\u2019\u00e9lection pr\u00e9sidentielle a lieu ce dimanche 10 avril 2022, pour lequel des candidats suivants voteriez-vous ?\nEn % des intentions de vote exprim\u00e9es (probabilit\u00e9 d\u2019aller voter notes 9 \u00e0 10)\nPhilippe POUTOU\nNathalie ARTHAUD\nFabien ROUSSEL\nJean-Luc MELENCHON\nAnne HIDALGO\nYannick JADOT\nEmmanuel MACRON\nVal\u00e9rie PECRESSE\nNicolas DUPONT-AIGNAN\nMarine LE PEN\n\u00c9ric ZEMMOUR\nJean LASSALLE 9% n\u2019expriment pas\nd\u2019intention de vote\nVoir marges d\u2019erreur\nslide 15\nAu 1er tour, l\u2019\u00e9cart n\u2019a jamais \u00e9t\u00e9 aussi serr\u00e9 entre Emmanuel Macron en baisse (26%, -2) et Marine Le\nPen (25%, +2) qui poursuit sa dynamique positive. Jean-Luc M\u00e9lenchon progresse et atteint 17.5% (+2).\nE. Zemmour (8.5%, -0.5) et V. P\u00e9cresse (8%, =) seraient distanc\u00e9s\n(-0,5)*\n(=)\n(=)\n(+2)\n(=)\n(-1)\n(-2)\n(=)\n(-0,5)\n(+0,5)\n(+2)\n(-0,5)\n(*) Evolutions par rapport \u00e0 l\u2019enqu\u00eate ELABE/BFMTV/L\u2019EXPRESS/SFR r\u00e9alis\u00e9e du 4 au 5 avril 2022\nLes Fran\u00e7ais et l'\u00e9lection pr\u00e9sidentielle 2022\n8 avril 2022\n ", "- 14 -\n1,5\n2,5 2,5 4\n4,5 4 4\n3,5 3,5 3,5 2,5 3,5\n2,5 2,5\n10 9 9,5 10 10,5\n11\n12,5 13\n14 15 15,5 15 15,5\n17,5\n2,5 2,5\n2\n1,5 1,5\n2,5\n1,5 1,5 1,5 1,5 2 1,5\n2 2\n6 5,5 4,5 4,5\n5,5 5,5\n6,5\n5 5\n4,5 4 4,5 5\n4\n22,5\n24\n25 26\n24 24,5 25\n33,5\n31\n27,5 28 28,5 28\n26\n16\n17\n16\n15 14\n11,5\n12\n10,5\n11,5 10\n9,5 8,5 8\n8\n2\n2\n2,5\n1,5\n2 2,5 2 2,5\n1,5\n3 2,5\n2,5\n2 2,5\n16,5\n16,5\n16,5\n15,5 15\n18 17\n15\n18\n20\n21\n22 23 25\n13,0 11,5 12,5 13,0 13,5 13,5 14,0\n11\n10,5 10\n10,5\n9,5 9 8,5\n2\n2\n1\n2\n1,5 1,5\n2 2,5 2 3 2,5 2,5\n3 2,5\nFabien ROUSSEL Jean-Luc MELENCHON Anne HIDALGO Yannick JADOT\nEmmanuel MACRON Val\u00e9rie PECRESSE Nicolas DUPONT-AIGNAN Marine LE PEN\nEric ZEMMOUR Jean LASSALE\n11.01\n2022\nEvolutions depuis le 11 janvier 2022\n26.01\n2022\n02.02\n2022\n08.02\n2022\n16.02\n2022\n22.02\n2022\n28.02\n2022\n08.03\n2022\n16.03\n2022\n21.03\n2022\n30.03\n2022\n01.04\n2022\n05.04\n2022\nLes Fran\u00e7ais et l'\u00e9lection pr\u00e9sidentielle 2022\n8 avril 2022\n08.04\n2022\n ", "- 15 -\nMarges d\u2019erreur de l\u2019intention de vote 1er tour\nExemple de lecture : Pour un r\u00e9sultat observ\u00e9 de 25%, il y a 95% de chances pour que le r\u00e9sultat r\u00e9el soit compris entre 22,3% et 27,7%.\n2,5\n8,5\n25,0\n2,5\n8,0\n26,0\n4,0\n2,0\n17,5\n2,5\n0,5\n1,0\nPhilippe POUTOU\nNathalie ARTHAUD\nFabien ROUSSEL\nJean-Luc MELENCHON\nAnne HIDALGO\nYannick JADOT\nEmmanuel MACRON\nVal\u00e9rie PECRESSE\nNicolas DUPONT-AIGNAN\nMarine LE PEN\n\u00c9ric ZEMMOUR\nJean LASSALLE\nLes Fran\u00e7ais et l'\u00e9lection pr\u00e9sidentielle 2022\n8 avril 2022\n ", "76% (+4 en 3 jours) des \u00e9lecteurs se disent s\u00fbrs de leur choix, 24% (-4) pourraient\nchanger d\u2019avis d\u2019ici dimanche\n76\n80\n84\n78\n85\n81\n51\n24\n20\n16\n22\n15\n19\n49\nJe suis s\u00fbr de mon choix Je pourrais changer d'avis d'ici \u00e0 l'\u00e9lection\nENSEMBLE\nJean-Luc MELENCHON\nEmmanuel MACRON\nVal\u00e9rie PECRESSE\nMarine LE PEN\n\u00c9ric ZEMMOUR\nVote blanc\nEn % - Inscrits sur les listes \u00e9lectorales (Probabilit\u00e9 d\u2019aller voter notes 9 \u00e0 10)\n- 16 -\n(-4)\n(+4)*\n(-4)\n(+4)\n(-2)\n(+2)\n(-4)\n(+4)\n(-1)\n(+1)\n(-2)\n(+2)\n(-11)\n(+11)\n(*) Evolutions par rapport \u00e0 l\u2019enqu\u00eate ELABE/BFMTV/L\u2019EXPRESS/SFR r\u00e9alis\u00e9e du 4 au 5 avril 2022\nLes Fran\u00e7ais et l'\u00e9lection pr\u00e9sidentielle 2022\n8 avril 2022\n ", "- 17 -\nAu 2nd tour, Emmanuel Macron (51%, -2) ne dispose plus que d\u2019une l\u00e9g\u00e8re avance sur Marine\nLe Pen (49%, +2) dans les intentions de vote\nQuestion : Au second tour de l\u2019\u00e9lection pr\u00e9sidentielle en 2022, si vous aviez le choix entre les candidats suivants, pour qui voteriez-vous ?\nEn % des intentions de vote exprim\u00e9es (probabilit\u00e9 d\u2019aller voter notes 9 \u00e0 10)\nVoir marges d\u2019erreur\nslide 19\n51\n49\nEmmanuel Macron\nMarine Le Pen\n(-2)*\n(+2)\n21% n\u2019ont pas exprim\u00e9 d\u2019intention de vote\n(*) Evolutions par rapport \u00e0 l\u2019enqu\u00eate ELABE/BFMTV/L\u2019EXPRESS/SFR r\u00e9alis\u00e9e du 4 au 5 avril 2022\nLes Fran\u00e7ais et l'\u00e9lection pr\u00e9sidentielle 2022\n8 avril 2022\n ", "- 18 -\nEvolutions depuis avril 2021\n56\n60 59 60\n55\n58\n55\n57\n54,5\n57\n56\n56 57\n55,5\n57,5\n61\n59,5\n56\n52,5\n53 53\n51\n44\n40 41 40\n45\n42\n45\n43 45,5\n43 44\n44\n43 44,5\n42,5\n39 41\n44\n47,5\n47 47\n49\nEmmanuel MACRON Marine LE PEN\n06.\n10\n27.\n10\n14.\n04\n29.\n06\n13.\n09\n11.\n11\n24.\n11\n21.\n12\n11.\n01\n26.\n01\n02.\n02\n08.\n02\n16.\n02\n2021 2022\n22.\n02\n28.\n02\n08.\n03\n16.\n03\n21.\n03\n30.\n03\n01.\n04\n05.\n04\nLes Fran\u00e7ais et l'\u00e9lection pr\u00e9sidentielle 2022\n8 avril 2022\n08.\n04\n ", "- 19 -\nMarges d\u2019erreur de l\u2019intention de vote 2nd tour\nExemple de lecture : Pour un r\u00e9sultat observ\u00e9 de 25%, il y a 95% de chances pour que le r\u00e9sultat r\u00e9el soit compris entre 22,3% et 27,7%.\n49\n51\n0 10 20 30 40 50 60 70 80\nEmmanuel MACRON\nMarine LE PEN\nLes Fran\u00e7ais et l'\u00e9lection pr\u00e9sidentielle 2022\n8 avril 2022\n ", "- 20 -\n40\n34\n99\n42\n1\n9\n24\n39\n25\n34\n99\n82\n11\n21\n41\n1\n24\n9\n65\nEmmanuel Macron Marine Le Pen Abstention, vote blanc\nEn % - Inscrits sur les listes \u00e9lectorales (Probabilit\u00e9 d\u2019aller voter notes 9 \u00e0 10)\nReports de voix du 1er tour au 2nd tour\nEmmanuel Macron / Marine Le Pen\nENSEMBLE\nJean-Luc MELENCHON\nEmmanuel MACRON\nVal\u00e9rie PECRESSE\nMarine LE PEN\n\u00c9ric ZEMMOUR\nAbstention, vote blanc\nLes Fran\u00e7ais et l'\u00e9lection pr\u00e9sidentielle 2022\n8 avril 2022\n ", "1\n0\n1\n10\n1\n1\n54\n2\n1\n22\n3\n2\n- 21 -\nQuestion : Selon vous, qui va gagner l\u2019\u00e9lection pr\u00e9sidentielle en avril 2022 ?\nEn %\nPlus d\u20191 Fran\u00e7ais sur 2 pronostique une r\u00e9\u00e9lection d\u2019Emmanuel Macron (54%, -6) malgr\u00e9 une\nbaisse. 22% (+2) anticipent une victoire de Marine Le Pen et 10% (+2) de Jean-Luc M\u00e9lenchon\n2% sans opinion\nPhilippe POUTOU\nNathalie ARTHAUD\nFabien ROUSSEL\nJean-Luc MELENCHON\nAnne HIDALGO\nYannick JADOT\nEmmanuel MACRON\nVal\u00e9rie PECRESSE\nNicolas DUPONT-AIGNAN\nMarine LE PEN\n\u00c9ric ZEMMOUR\nJean LASSALLE\n(=)\n(=)*\n(+1)\n(+2)\n(+1)\n(=)\n(-6)\n(+2)\n(=)\n5 7\n8\n10 8 10\n48\n55\n64\n57 60\n54\n14 9\n4 3 2 2\n14 11 13\n20 20 22\n6\n9\n5\n4 4 3\nJean-Luc MELENCHON Emmanuel MACRON\nVal\u00e9rie PECRESSE Marine LE PEN\nEric ZEMMOUR\nEVOLUTIONS\n17.\n01\n16.\n02\n21.\n03\n01.\n04\n(=)\n(+1)\n(-1)\n05.\n04\n(*) Evolutions par rapport \u00e0 l\u2019enqu\u00eate ELABE/BFMTV/L\u2019EXPRESS/SFR r\u00e9alis\u00e9e du 4 au 5 avril 2022\nLes Fran\u00e7ais et l'\u00e9lection pr\u00e9sidentielle 2022\n8 avril 2022\n08.\n04\n ", "- 22 -\nPronostic de victoire \u00e0 l\u2019\u00e9lection pr\u00e9sidentielle par \u00e9lectorats potentiels\nJean-Luc\nMELENCHON\nEmmanuel\nMACRON\nVal\u00e9rie\nPECRESSE\nMarine\nLE PEN\n\u00c9ric\nZEMMOUR\nElecteurs potentiels de\nJ-L. MELENCHON 52 36 1 8 0\nElecteurs potentiels de\nE. MACRON 0 98 0 1 0\nElecteurs potentiels de\nV. PECRESSE 0 62 28 8 0\nElecteurs potentiels de\nM. LE PEN 0 24 0 73 1\nElecteurs potentiels de\nE. ZEMMOUR 1 38 0 30 31\nEn %\nLes Fran\u00e7ais et l'\u00e9lection pr\u00e9sidentielle 2022\n8 avril 2022\n ", "- 23 -\nEn % Note 10 Notes 9 \u00e0 10\nEnsemble 65 78\nSEXE DU REPONDANT\nHomme 65 78\nFemme 65 78\nAGE DU REPONDANT\n18-24 ans 60 70\n25-34 ans 58 71\n35-49 ans 61 73\n50-64 ans 69 83\n65 ans et plus 71 85\nPROFESSION DU REPONDANT\nActifs 63 76\nArtisan, commer\u00e7ant (*) 71 79\nCSP+ 65 79\nCadre, profession intellectuelle sup. 64 78\nProfession interm\u00e9diaire 67 79\nCSP- 60 73\nEmploy\u00e9 63 75\nOuvrier 54 71\nInactifs 69 81\nRetrait\u00e9 71 85\nAutre Inactif 63 71\nCATEGORIE D'AGGLOMERATION\nCommunes rurales 73 83\nCommunes urbaines de province 64 78\nDe 2.000 \u00e0 moins de 20.000 hab. 65 79\nDe 20.000 \u00e0 moins de 100.000 hab. 66 82\n100.000 hab. et plus 63 76\nAgglom\u00e9ration parisienne 60 71\nREGION DE RESIDENCE (UDA5)\nR\u00e9gion parisienne 61 72\nProvince 66 79\nNord-est 63 77\nNord-ouest 69 78\nSud-ouest 70 81\nSud-est 66 82\nD\u00e9tail des r\u00e9sultats\nPar cat\u00e9gories sociod\u00e9mographiques et professionnelles\nSur une \u00e9chelle allant de \u00ab 0 \u00bb \u00e0 \u00ab 10 \u00bb, quelle est la probabilit\u00e9 que vous alliez voter \u00e0 l\u2019\u00e9lection pr\u00e9sidentielle qui aura lieu ce dimanche 10 avril 2022 ?\n* R\u00e9sultats \u00e0 interpr\u00e9ter avec prudence compte-tenu des effectifs de r\u00e9pondants\nLes Fran\u00e7ais et l'\u00e9lection pr\u00e9sidentielle 2022\n8 avril 2022\n ", "- 24 -\nD\u00e9tail des r\u00e9sultats\nSelon la pr\u00e9f\u00e9rence partisane et le vote \u00e0 la pr\u00e9sidentielle\nSur une \u00e9chelle allant de \u00ab 0 \u00bb \u00e0 \u00ab 10 \u00bb, quelle est la probabilit\u00e9 que vous alliez voter \u00e0 l\u2019\u00e9lection pr\u00e9sidentielle qui aura lieu ce dimanche 10 avril 2022 ?\n* R\u00e9sultats \u00e0 interpr\u00e9ter avec prudence compte-tenu des effectifs de r\u00e9pondants\nEn % Note 10 Notes 9 \u00e0 10\nEnsemble 65 78\nPREFERENCE PARTISANE\nTOTAL GAUCHE 66 79\nLa France Insoumise (*) 64 76\nEurope Ecologie-Les Verts 65 80\nParti Socialiste / G\u00e9n\u00e9ration.s / PRG 66 78\nTOTAL EN MARCHE / MODEM 71 87\nLa R\u00e9publique en Marche ! 73 87\nTOTAL DROITE 72 85\nLes R\u00e9publicains 71 83\nTOTAL RN/R! 79 88\nLe Rassemblement National 77 87\nReconqu\u00eate! 83 90\nSans pr\u00e9f\u00e9rence partisane 55 68\nVOTE PRESIDENTIELLE 2017 (1ER TOUR)\nJean-Luc MELENCHON 63 76\nBeno\u00eet HAMON 69 82\nEmmanuel MACRON 69 86\nFran\u00e7ois FILLON 78 89\nMarine LE PEN 74 85\nAbstention, vote blanc ou nul 49 61\nVOTE PRESIDENTIELLE 2017 (2ND TOUR)\nEmmanuel MACRON 66 81\nMarine LE PEN 77 86\nAbstention, vote blanc ou nul 57 69\nLes Fran\u00e7ais et l'\u00e9lection pr\u00e9sidentielle 2022\n8 avril 2022\n ", "- 25 -\nD\u00e9tail des r\u00e9sultats\nPar cat\u00e9gories sociod\u00e9mographiques et professionnelles\nLe premier tour de l\u2019\u00e9lection pr\u00e9sidentielle a lieu ce dimanche 10 avril 2022, pour lequel des candidats suivants voteriez-vous ?\n* R\u00e9sultats \u00e0 interpr\u00e9ter avec prudence compte-tenu des effectifs de r\u00e9pondants\nEn % des intentions de vote exprim\u00e9es\nP.\nPoutou\nN.\nArthaud\nF.\nRoussel\nJ.-L.\nM\u00e9lenchon\nA.\nHidalgo\nY.\nJadot\nE.\nMacron\nV.\nP\u00e9cresse\nN. Dupont-\nAignan\nM.\nLe Pen\nE.\nZemmour\nJ.\nLassalle\nAucune\nintention de\nvote exprim\u00e9e\nEnsemble 1 0,5 2,5 17,5 2 4 26 8 2,5 25 8,5 2,5 9\nSEXE DU REPONDANT\nHomme 1 0 3 21 3 4 24 7 3 22 10 2 7\nFemme 1 1 2 14 2 4 28 8 2 27 8 3 10\nAGE DU REPONDANT\n18-24 ans (*) 1 0 0 28 0 9 25 2 1 26 6 2 11\n25-34 ans 1 1 4 26 4 2 19 4 4 29 4 2 7\n35-49 ans 2 1 1 21 3 3 24 6 1 28 8 2 11\n50-64 ans 2 1 3 14 2 5 22 9 4 28 7 3 8\n65 ans et plus 0 0 3 12 1 3 34 11 2 18 13 3 7\nPROFESSION DU REPONDANT\nActifs 1 1 2 20 3 4 22 7 3 28 6 3 8\nArtisan, commer\u00e7ant (*) 0 0 1 8 0 3 20 8 4 41 13 2 5\nCSP+ 1 0 4 21 4 5 29 10 2 17 4 3 7\nCadre, profession intellectuelle sup. 2 0 2 22 4 6 34 10 2 9 5 4 7\nProfession interm\u00e9diaire 1 1 5 20 4 4 25 10 2 22 4 2 9\nCSP- 1 1 2 21 2 3 17 4 3 37 7 2 10\nEmploy\u00e9 2 1 3 22 3 3 17 3 4 35 6 1 10\nOuvrier 1 1 0 20 2 2 16 5 2 39 8 4 9\nInactifs 1 0 2 15 1 4 31 9 2 21 12 2 8\nRetrait\u00e9 0 0 3 11 1 4 33 11 2 19 13 3 7\nAutre Inactif 2 0 1 25 0 8 23 2 2 29 6 2 13\nCATEGORIE D'AGGLOMERATION\nCommunes rurales 2 1 3 11 1 6 26 7 3 29 8 3 10\nCommunes urbaines de province 1 0 2 19 2 2 27 7 3 25 9 3 8\nDe 2.000 \u00e0 moins de 20.000 hab. 2 1 1 18 1 2 25 7 3 28 9 3 10\nDe 20.000 \u00e0 moins de 100.000 hab. 1 0 2 17 2 2 22 9 4 29 9 3 9\n100.000 hab. et plus 0 0 3 20 2 3 30 7 3 22 8 2 7\nAgglom\u00e9ration parisienne 0 0 4 23 4 7 23 12 1 17 8 1 6\nREGION DE RESIDENCE (UDA5)\nR\u00e9gion parisienne 0 1 3 22 4 7 24 13 1 17 7 1 7\nProvince 1 0 2 17 2 3 26 7 3 27 9 3 9\nNord-est 2 0 3 20 2 3 20 8 3 27 10 2 11\nNord-ouest 1 1 3 15 1 5 28 8 4 25 6 3 9\nSud-ouest 2 1 2 14 2 4 22 3 1 33 12 4 7\nSud-est 0 0 1 16 2 2 32 7 3 25 9 3 8\nLes Fran\u00e7ais et l'\u00e9lection pr\u00e9sidentielle 2022\n8 avril 2022\n ", "- 26 -\nD\u00e9tail des r\u00e9sultats\nSelon la pr\u00e9f\u00e9rence partisane et le vote \u00e0 la pr\u00e9sidentielle\nLe premier tour de l\u2019\u00e9lection pr\u00e9sidentielle a lieu ce dimanche 10 avril 2022, pour lequel des candidats suivants voteriez-vous ?\n* R\u00e9sultats \u00e0 interpr\u00e9ter avec prudence compte-tenu des effectifs de r\u00e9pondants\nEn % des intentions de vote exprim\u00e9es\nP.\nPoutou\nN.\nArthaud\nF.\nRoussel\nJ.-L.\nM\u00e9lenchon\nA.\nHidalgo\nY.\nJadot\nE.\nMacron\nV.\nP\u00e9cresse\nN. Dupont-\nAignan\nM.\nLe Pen\nE.\nZemmour\nJ.\nLassalle\nAucune\nintention de\nvote\nexprim\u00e9e\nEnsemble 1 0,5 2,5 17,5 2 4 26 8 2,5 25 8,5 2,5 9\nPREFERENCE PARTISANE\nTOTAL GAUCHE 0 0 7 51 7 13 13 1 1 5 1 1 2\nLa France Insoumise (*) 0 0 0 93 0 0 0 0 2 5 0 0 0\nEurope Ecologie-Les Verts 0 0 1 30 5 43 13 0 1 4 1 2 3\nParti Socialiste / G\u00e9n\u00e9ration.s / PRG 0 1 6 32 17 4 29 1 0 7 2 1 5\nTOTAL EN MARCHE / MODEM 0 0 0 3 1 1 87 3 1 2 1 1 1\nLa R\u00e9publique en Marche ! 0 0 0 2 0 1 92 2 0 2 1 0 1\nTOTAL DROITE 0 0 1 6 0 0 23 37 8 18 5 2 4\nLes R\u00e9publicains 0 0 0 3 0 0 25 46 1 19 5 1 1\nTOTAL RN/R! 0 0 0 0 0 0 1 0 0 69 30 0 0\nLe Rassemblement National 0 0 0 0 0 0 1 0 0 92 7 0 0\nReconqu\u00eate! 0 0 0 0 0 0 0 0 0 6 93 1 1\nSans pr\u00e9f\u00e9rence partisane 2 1 3 14 1 3 30 7 4 24 5 6 23\nVOTE PRESIDENTIELLE 2017 (1ER TOUR)\nJean-Luc MELENCHON 1 1 9 59 2 6 4 1 1 9 3 4 2\nBeno\u00eet HAMON 2 1 2 32 17 8 21 2 0 11 2 2 6\nEmmanuel MACRON 0 0 1 6 2 5 76 3 2 3 1 1 5\nFran\u00e7ois FILLON 0 0 1 2 1 2 24 32 3 17 16 2 2\nMarine LE PEN 0 0 0 1 0 0 5 3 1 76 13 1 1\nAbstention, vote blanc ou nul (*) 1 1 0 29 2 7 21 3 1 26 7 2 30\nVOTE PRESIDENTIELLE 2017 (2ND TOUR)\nEmmanuel MACRON 1 0 3 15 3 5 50 9 2 7 3 2 7\nMarine LE PEN 1 1 0 3 1 0 1 6 2 62 22 1 3\nAbstention, vote blanc ou nul (*) 1 1 4 35 1 5 10 9 3 21 6 4 16\nLes Fran\u00e7ais et l'\u00e9lection pr\u00e9sidentielle 2022\n8 avril 2022\n ", "- 27 -\nD\u00e9tail des r\u00e9sultats\nPar cat\u00e9gories sociod\u00e9mographiques et professionnelles\nAu second tour de l\u2019\u00e9lection pr\u00e9sidentielle en 2022, si vous aviez le choix entre les candidats suivants, pour qui voteriez-vous ?\n* R\u00e9sultats \u00e0 interpr\u00e9ter avec prudence compte-tenu des effectifs de r\u00e9pondants\nEn % des intentions de vote exprim\u00e9es Emmanuel Macron Marine Le Pen Aucune intention de vote\nEnsemble 51 49 21\nSEXE DU REPONDANT\nHomme 50 50 21\nFemme 52 48 20\nAGE DU REPONDANT\n18-24 ans (*) 60 40 20\n25-34 ans 40 60 21\n35-49 ans 51 49 18\n50-64 ans 47 53 21\n65 ans et plus 57 43 22\nPROFESSION DU REPONDANT\nActifs 48 52 20\nArtisan, commer\u00e7ant (*) 39 61 16\nCSP+ 62 38 25\nCadre, profession intellectuelle sup. 73 27 25\nProfession interm\u00e9diaire 55 45 24\nCSP- 36 64 16\nEmploy\u00e9 37 63 17\nOuvrier 35 65 16\nInactifs 56 44 21\nRetrait\u00e9 56 44 21\nAutre Inactif 55 45 22\nCATEGORIE D'AGGLOMERATION\nCommunes rurales 49 51 20\nCommunes urbaines de province 50 50 21\nDe 2.000 \u00e0 moins de 20.000 hab. 47 53 23\nDe 20.000 \u00e0 moins de 100.000 hab. 44 56 16\n100.000 hab. et plus 55 45 21\nAgglom\u00e9ration parisienne 57 43 21\nREGION DE RESIDENCE (UDA5)\nR\u00e9gion parisienne 58 42 21\nProvince 50 50 20\nNord-est 47 53 23\nNord-ouest 55 45 21\nSud-ouest 38 62 23\nSud-est 53 47 17\nLes Fran\u00e7ais et l'\u00e9lection pr\u00e9sidentielle 2022\n8 avril 2022\n ", "- 28 -\nD\u00e9tail des r\u00e9sultats\nSelon la pr\u00e9f\u00e9rence partisane et le vote \u00e0 la pr\u00e9sidentielle\nAu second tour de l\u2019\u00e9lection pr\u00e9sidentielle en 2022, si vous aviez le choix entre les candidats suivants, pour qui voteriez-vous ?\n* R\u00e9sultats \u00e0 interpr\u00e9ter avec prudence compte-tenu des effectifs de r\u00e9pondants\nEn % des intentions de vote exprim\u00e9es Emmanuel Macron Marine Le Pen\nAucune intention de\nvote\nEnsemble 51 49 21\nPREFERENCE PARTISANE\nTOTAL GAUCHE 71 29 36\nLa France Insoumise (*) 51 49 37\nEurope Ecologie-Les Verts 79 21 33\nParti Socialiste / G\u00e9n\u00e9ration.s / PRG 84 16 28\nTOTAL EN MARCHE / MODEM 97 3 0\nLa R\u00e9publique en Marche ! 99 1 0\nTOTAL DROITE 53 47 17\nLes R\u00e9publicains 54 46 15\nTOTAL RN/R! 2 98 4\nLe Rassemblement National 2 98 1\nReconqu\u00eate! 2 98 12\nSans pr\u00e9f\u00e9rence partisane 52 48 29\nVOTE PRESIDENTIELLE 2017 (1ER TOUR)\nJean-Luc MELENCHON 44 56 39\nBeno\u00eet HAMON 75 25 35\nEmmanuel MACRON 95 5 8\nFran\u00e7ois FILLON 48 52 17\nMarine LE PEN 7 93 4\nAbstention, vote blanc ou nul (*) 53 47 33\nVOTE PRESIDENTIELLE 2017 (2ND TOUR)\nEmmanuel MACRON 85 15 12\nMarine LE PEN 2 98 5\nAbstention, vote blanc ou nul (*) 38 62 45\nLes Fran\u00e7ais et l'\u00e9lection pr\u00e9sidentielle 2022\n8 avril 2022\n ", "- 29 -\nD\u00e9tail des r\u00e9sultats\nPar cat\u00e9gories sociod\u00e9mographiques et professionnelles\nSelon vous, qui va gagner l\u2019\u00e9lection pr\u00e9sidentielle en avril 2022 ?\n* R\u00e9sultats \u00e0 interpr\u00e9ter avec prudence compte-tenu des effectifs de r\u00e9pondants\nEn %\nP.\nPoutou\nN.\nArthaud\nF.\nRoussel\nJ.-L.\nM\u00e9lenchon\nA.\nHidalgo\nY.\nJadot\nE.\nMacron\nV.\nP\u00e9cresse\nN. Dupont-\nAignan\nM.\nLe Pen\nE.\nZemmour\nJ.\nLassalle\nSans opinion\nEnsemble 1 0 1 10 1 1 54 2 1 22 3 2 2\nSEXE DU REPONDANT\nHomme 0 0 1 12 1 1 52 2 1 22 4 2 2\nFemme 1 0 0 8 0 1 57 3 1 23 3 1 2\nAGE DU REPONDANT\n18-24 ans (*) 1 0 0 18 1 2 51 2 0 18 4 1 2\n25-34 ans 1 1 2 18 1 1 43 2 1 23 3 2 2\n35-49 ans 1 0 0 7 2 1 57 1 1 22 3 2 3\n50-64 ans 1 1 0 7 0 1 54 3 1 26 3 1 2\n65 ans et plus 1 0 0 6 0 1 61 3 1 20 4 1 2\nPROFESSION DU REPONDANT\nActifs 1 0 1 10 1 1 53 2 1 23 3 2 2\nArtisan, commer\u00e7ant (*) 2 0 0 12 0 1 41 7 4 27 4 2 0\nCSP+ 0 0 1 9 2 0 63 2 0 16 2 2 3\nCadre, profession intellectuelle sup. 1 0 1 10 2 1 71 1 0 9 2 1 1\nProfession interm\u00e9diaire 0 0 1 8 1 0 58 3 0 20 2 3 4\nCSP- 1 1 0 11 1 1 46 2 1 28 3 2 3\nEmploy\u00e9 1 0 1 11 0 1 48 2 1 26 3 2 4\nOuvrier 1 1 0 11 1 1 43 3 0 32 3 2 2\nInactifs 1 0 0 9 0 1 57 2 1 22 4 1 2\nRetrait\u00e9 1 0 0 5 0 1 60 3 1 22 4 1 2\nAutre Inactif 1 0 0 17 0 1 49 2 2 22 3 1 2\nCATEGORIE D'AGGLOMERATION\nCommunes rurales 1 1 1 6 1 1 52 1 0 28 2 2 4\nCommunes urbaines de province 0 0 0 10 1 1 54 3 1 23 3 2 2\nDe 2.000 \u00e0 moins de 20.000 hab. 0 0 0 9 0 1 54 1 0 27 4 3 1\nDe 20.000 \u00e0 moins de 100.000 hab. 1 0 0 9 0 2 57 4 1 21 3 0 2\n100.000 hab. et plus 0 0 1 12 1 1 53 2 1 21 3 2 3\nAgglom\u00e9ration parisienne 2 0 0 13 1 1 59 4 1 14 4 0 1\nREGION DE RESIDENCE (UDA5)\nR\u00e9gion parisienne 2 0 0 13 1 2 58 3 1 15 4 0 1\nProvince 1 0 0 9 1 1 54 2 1 24 3 2 2\nNord-est 1 0 1 9 1 1 54 2 0 26 1 2 2\nNord-ouest 0 1 1 9 0 1 55 3 1 21 4 2 2\nSud-ouest 1 0 0 9 0 1 46 2 1 29 4 3 4\nSud-est 1 0 0 9 1 0 55 2 1 24 4 1 2\nLes Fran\u00e7ais et l'\u00e9lection pr\u00e9sidentielle 2022\n8 avril 2022\n ", "- 30 -\nD\u00e9tail des r\u00e9sultats\nSelon la pr\u00e9f\u00e9rence partisane et le vote \u00e0 la pr\u00e9sidentielle\nSelon vous, qui va gagner l\u2019\u00e9lection pr\u00e9sidentielle en avril 2022 ?\n* R\u00e9sultats \u00e0 interpr\u00e9ter avec prudence compte-tenu des effectifs de r\u00e9pondants\nEn %\nP.\nPoutou\nN.\nArthaud\nF.\nRoussel\nJ.-L.\nM\u00e9lenchon\nA.\nHidalgo\nY.\nJadot\nE.\nMacron\nV.\nP\u00e9cresse\nN. Dupont-\nAignan\nM.\nLe Pen\nE.\nZemmour\nJ.\nLassalle\nSans\nopinion\nEnsemble 1 0 1 10 1 1 54 2 1 22 3 2 2\nPREFERENCE PARTISANE\nTOTAL GAUCHE 0 0 2 27 2 2 53 1 1 9 0 1 2\nLa France Insoumise (*) 0 0 0 60 0 0 33 0 0 6 0 0 1\nEurope Ecologie-Les Verts 0 0 0 11 0 8 68 1 2 6 0 2 2\nParti Socialiste / G\u00e9n\u00e9ration.s / PRG 1 0 0 10 4 0 64 1 2 14 1 0 3\nTOTAL EN MARCHE / MODEM 0 0 0 0 0 1 96 0 1 2 0 0 0\nLa R\u00e9publique en Marche ! 0 0 0 0 0 1 97 0 0 2 0 0 0\nTOTAL DROITE 0 0 0 4 0 1 63 10 3 17 1 0 1\nLes R\u00e9publicains 0 0 0 2 0 0 68 12 1 16 1 0 0\nTOTAL RN/R! 0 0 0 0 0 0 24 0 0 60 14 1 1\nLe Rassemblement National 1 0 0 0 0 0 21 0 0 74 3 0 1\nReconqu\u00eate! 0 0 0 0 0 0 32 0 0 20 46 2 0\nSans pr\u00e9f\u00e9rence partisane 1 0 1 8 0 1 55 3 0 22 2 3 4\nVOTE PRESIDENTIELLE 2017 (1ER TOUR)\nJean-Luc MELENCHON 1 1 2 32 1 1 44 0 1 15 0 0 2\nBeno\u00eet HAMON 2 0 1 15 3 1 58 3 0 13 1 1 2\nEmmanuel MACRON 0 0 0 2 0 1 89 1 0 5 0 1 1\nFran\u00e7ois FILLON 1 0 0 2 0 1 61 8 1 21 5 0 0\nMarine LE PEN 0 0 0 1 0 1 26 1 0 62 7 0 2\nAbstention, vote blanc ou nul (*) 2 0 1 10 1 1 53 2 1 21 2 3 3\nVOTE PRESIDENTIELLE 2017 (2ND TOUR)\nEmmanuel MACRON 0 0 1 7 0 1 77 2 1 8 1 1 1\nMarine LE PEN 1 0 0 3 0 1 24 2 0 58 9 1 1\nAbstention, vote blanc ou nul (*) 1 0 1 17 1 1 47 3 1 20 2 2 4\nLes Fran\u00e7ais et l'\u00e9lection pr\u00e9sidentielle 2022\n8 avril 2022\n ", "14 place Marie-Jeanne Bassot\n92300 Levallois / Fr\nT\u00e9l. +33 (0)1 57 64 01 60\n@elabe_fr\nwww.elabe.fr\n "], "mostRead": [0, 0, 0, 0, 0, 0, 0, 0, 0, 0, 0, 0, 0, 0, 0, 0, 0, 0, 0, 0, 0, 0, 0, 0, 0, 0, 0, 0, 0, 0, 0]}