{"id": "11165358", "presentation_url": "https://fr.slideshare.net/slideshow/les-biopics-franais/11165358", "title": "Les biopics fran\u00e7ais", "author": "panoramix", "date": "2012-01-19", "len": 12, "description": "Quelques affiches de biopics fran\u00e7ais.", "lang": "fr", "dim": {"height": 540, "width": 720}, "like": 0, "view": 592, "transcript": ["LES BIOPICS FRAN\u00c7AIS \u00ab\u00a0 biopic \u00a0\u00bb ( contraction  de \u00ab\u00a0 biographical motion true picture \u00a0\u00bb) ", "\u00a0", "\u00a0", "\u00a0", "\u00a0", "\u00a0", "\u00a0", "\u00a0", "\u00a0", "\u00a0", "\u00a0", "Madrid janvier 2012 FIN "], "mostRead": [0, 0, 0, 0, 0, 0, 0, 0, 0, 0, 0, 0]}